<?xml version = '1.0' encoding = 'UTF-8'?>
<Diagram class="oracle.dbtools.crest.swingui.relational.DPVRelational" name="Relational_1" id="B8B1F8B7-01B9-7849-86E7-215789E83B2F">
<createdBy>alex7</createdBy>
<modifiedBy>alex7</modifiedBy>
<createdTime>2022-03-12 15:29:34 UTC</createdTime>
<autoRoute>false</autoRoute>
<boxInbox>true</boxInbox>
<showLegend>false</showLegend>
<showLabels>false</showLabels>
<showRelAttributes>false</showRelAttributes>
<gridEnabled>false</gridEnabled>
<showGrid>false</showGrid>
<diagramColor>-1</diagramColor>
<display>false</display>
<notation>1</notation>
<objectViews>
<OView class="oracle.dbtools.crest.swingui.relational.TVTable" oid="506C86DD-B4CB-9E4B-FFB3-F02D11D7321F" otype="Table" vid="165BB2FE-57C0-6B88-F330-6AB2073E6F36">
<hideElementsInCurrentOnly>false</hideElementsInCurrentOnly>
<bounds x="53" y="507" width="219" height="97"/>
</OView>
<OView class="oracle.dbtools.crest.swingui.relational.TVTable" oid="563F40C8-6420-5C36-E9B4-AFE2EF5C8FCD" otype="Table" vid="4CB0BF3F-E84E-5866-3DA9-D666FFBE4EFB">
<hideElementsInCurrentOnly>false</hideElementsInCurrentOnly>
<bounds x="759" y="277" width="246" height="131"/>
</OView>
<OView class="oracle.dbtools.crest.swingui.relational.TVTable" oid="6CCCA07C-C7CD-531B-172A-C65A37F068AE" otype="Table" vid="4A79820B-F432-67BC-A176-875C50AE00CD">
<hideElementsInCurrentOnly>false</hideElementsInCurrentOnly>
<bounds x="381" y="664" width="229" height="105"/>
</OView>
<OView class="oracle.dbtools.crest.swingui.relational.TVTable" oid="6FFF78B2-3146-BBD0-7D15-C6E9C860338D" otype="Table" vid="A2D9AAC0-7E6B-C4BD-FD60-A3925C8425FC">
<hideElementsInCurrentOnly>false</hideElementsInCurrentOnly>
<bounds x="383" y="4" width="248" height="128"/>
</OView>
<OView class="oracle.dbtools.crest.swingui.relational.TVTable" oid="A0C60799-EEC0-2744-F11A-2E5BCEAAFD19" otype="Table" vid="66397D4A-9EB5-788D-4EB0-4935A7622B31">
<hideElementsInCurrentOnly>false</hideElementsInCurrentOnly>
<bounds x="372" y="182" width="258" height="136"/>
</OView>
<OView class="oracle.dbtools.crest.swingui.relational.TVTable" oid="A406CDB3-408B-6B72-0273-0706FACB0BC2" otype="Table" vid="60F93F51-14A9-AEFE-5B42-3760D9B40929">
<hideElementsInCurrentOnly>false</hideElementsInCurrentOnly>
<bounds x="27" y="283" width="251" height="154"/>
</OView>
<OView class="oracle.dbtools.crest.swingui.relational.TVTable" oid="D68DE5A5-3CB6-BC10-F791-53F8EFA1D8BF" otype="Table" vid="8CBAAAD1-7A3D-9A8C-58D4-4940479366F2">
<hideElementsInCurrentOnly>false</hideElementsInCurrentOnly>
<bounds x="772" y="510" width="230" height="99"/>
</OView>
<OView class="oracle.dbtools.crest.swingui.relational.TVTable" oid="DC08962B-A69F-22C8-1E86-37629903A6E2" otype="Table" vid="3312EA5A-E5B7-4BBB-E44F-D16D4FAFD0D1">
<hideElementsInCurrentOnly>false</hideElementsInCurrentOnly>
<bounds x="354" y="387" width="283" height="226"/>
</OView>
</objectViews>
<connectors>
<Connector class="oracle.dbtools.crest.swingui.relational.TVFKRelation" oid="004BC88F-328C-EA3E-6677-A4EA28CDFC1A" otype="FKIndexAssociation" vid_source="3312EA5A-E5B7-4BBB-E44F-D16D4FAFD0D1" vid_target="60F93F51-14A9-AEFE-5B42-3760D9B40929">
<hideElementsInCurrentOnly>false</hideElementsInCurrentOnly>
<backgroundColor>-16777216</backgroundColor>
<lineWidth>1</lineWidth>
<points>
<point x="354" y="412"/>
<point x="278" y="412"/>
</points>
</Connector>
<Connector class="oracle.dbtools.crest.swingui.relational.TVFKRelation" oid="0558F36F-5326-8261-4773-0E659B51F10D" otype="FKIndexAssociation" vid_source="8CBAAAD1-7A3D-9A8C-58D4-4940479366F2" vid_target="3312EA5A-E5B7-4BBB-E44F-D16D4FAFD0D1">
<hideElementsInCurrentOnly>false</hideElementsInCurrentOnly>
<backgroundColor>-16777216</backgroundColor>
<lineWidth>1</lineWidth>
<points>
<point x="772" y="559"/>
<point x="637" y="559"/>
</points>
</Connector>
<Connector class="oracle.dbtools.crest.swingui.relational.TVFKRelation" oid="149D90B9-6A39-BBC6-AA5F-A2479DAC1984" otype="FKIndexAssociation" vid_source="66397D4A-9EB5-788D-4EB0-4935A7622B31" vid_target="4CB0BF3F-E84E-5866-3DA9-D666FFBE4EFB">
<hideElementsInCurrentOnly>false</hideElementsInCurrentOnly>
<backgroundColor>-16777216</backgroundColor>
<lineWidth>1</lineWidth>
<points>
<point x="630" y="297"/>
<point x="759" y="297"/>
</points>
</Connector>
<Connector class="oracle.dbtools.crest.swingui.relational.TVFKRelation" oid="21C671DD-485A-EC91-8518-FD79BC80C928" otype="FKIndexAssociation" vid_source="A2D9AAC0-7E6B-C4BD-FD60-A3925C8425FC" vid_target="66397D4A-9EB5-788D-4EB0-4935A7622B31">
<hideElementsInCurrentOnly>false</hideElementsInCurrentOnly>
<backgroundColor>-16777216</backgroundColor>
<lineWidth>1</lineWidth>
<points>
<point x="506" y="132"/>
<point x="506" y="182"/>
</points>
</Connector>
<Connector class="oracle.dbtools.crest.swingui.relational.TVFKRelation" oid="2CD907F5-EB1B-1D12-26C0-780A11618928" otype="FKIndexAssociation" vid_source="66397D4A-9EB5-788D-4EB0-4935A7622B31" vid_target="60F93F51-14A9-AEFE-5B42-3760D9B40929">
<hideElementsInCurrentOnly>false</hideElementsInCurrentOnly>
<backgroundColor>-16777216</backgroundColor>
<lineWidth>1</lineWidth>
<points>
<point x="372" y="300"/>
<point x="278" y="300"/>
</points>
</Connector>
<Connector class="oracle.dbtools.crest.swingui.relational.TVFKRelation" oid="502C17CC-3BCC-81F3-4F19-B4CC76122129" otype="FKIndexAssociation" vid_source="4A79820B-F432-67BC-A176-875C50AE00CD" vid_target="3312EA5A-E5B7-4BBB-E44F-D16D4FAFD0D1">
<hideElementsInCurrentOnly>false</hideElementsInCurrentOnly>
<backgroundColor>-16777216</backgroundColor>
<lineWidth>1</lineWidth>
<points>
<point x="495" y="664"/>
<point x="495" y="613"/>
</points>
</Connector>
<Connector class="oracle.dbtools.crest.swingui.relational.TVFKRelation" oid="603D9E9A-E1C1-CFD4-5824-B85F6FBDE2FE" otype="FKIndexAssociation" vid_source="165BB2FE-57C0-6B88-F330-6AB2073E6F36" vid_target="3312EA5A-E5B7-4BBB-E44F-D16D4FAFD0D1">
<hideElementsInCurrentOnly>false</hideElementsInCurrentOnly>
<backgroundColor>-16777216</backgroundColor>
<lineWidth>1</lineWidth>
<points>
<point x="272" y="555"/>
<point x="354" y="555"/>
</points>
</Connector>
<Connector class="oracle.dbtools.crest.swingui.relational.TVFKRelation" oid="A915226D-C9B3-C3DA-9ACE-7ABF1195B376" otype="FKIndexAssociation" vid_source="66397D4A-9EB5-788D-4EB0-4935A7622B31" vid_target="3312EA5A-E5B7-4BBB-E44F-D16D4FAFD0D1">
<hideElementsInCurrentOnly>false</hideElementsInCurrentOnly>
<backgroundColor>-16777216</backgroundColor>
<lineWidth>1</lineWidth>
<points>
<point x="501" y="318"/>
<point x="501" y="387"/>
</points>
</Connector>
<Connector class="oracle.dbtools.crest.swingui.relational.TVFKRelation" oid="BA3315AE-8447-495C-1BBF-D6EA6AF1D7C0" otype="FKIndexAssociation" vid_source="3312EA5A-E5B7-4BBB-E44F-D16D4FAFD0D1" vid_target="4CB0BF3F-E84E-5866-3DA9-D666FFBE4EFB">
<hideElementsInCurrentOnly>false</hideElementsInCurrentOnly>
<backgroundColor>-16777216</backgroundColor>
<lineWidth>1</lineWidth>
<points>
<point x="637" y="397"/>
<point x="759" y="397"/>
</points>
</Connector>
</connectors>
</Diagram>